astea/__init__.py
astea/index_types.py
astea/main.py
astea/utils.py
astea-1.4.dist-info/LICENSE
astea-1.4.dist-info/WHEEL
astea-1.4.dist-info/METADATA
astea-1.4.dist-info/RECORD
